py_static_check
