Metadata-Version: 1.0
Name: py-static-check
Version: 1.2
Summary: Statically check your Python code
Home-page: http://www.amix.dk/
Author: amix
Author-email: amix@amix.dk
License: MIT
Platform: UNKNOWN
Classifier: Development Status :: 6 - Mature
Classifier: Environment :: Console
Classifier: Intended Audience :: Developers
Classifier: License :: OSI Approved :: MIT License
Classifier: Programming Language :: Python
Classifier: Topic :: Software Development
Classifier: Topic :: Utilities
